{
  "model_name": "GRU",
  "stop_epoch": 44,
  "best_epoch": 3,
  "best_val_loss": 0.0001427539083066803,
  "min_epochs": 20,
  "patience": 25,
  "min_delta": 1e-05,
  "val_loss_smooth_window": 3,
  "train_log_every": 1,
  "scheduler_type": "plateau",
  "scheduler_factor": 0.5,
  "scheduler_patience": 5,
  "scheduler_min_lr": 1e-06,
  "figure_hyperparameters": "Hyperparameters: batch_size=64, epochs=100, hidden=32, layers=3, learning_rate=0.001, min_delta=1e-05, min_epochs=20, patience=25, scheduler_factor=0.5, scheduler_min_lr=1e-06, scheduler_patience=5, scheduler_type=plateau, val_loss_smooth_window=3",
  "epochs": [
    {
      "epoch": 1,
      "train_loss": 0.0003970937970850567,
      "val_loss": 0.00015338046597350536,
      "val_loss_for_stop": 0.00015338046597350536,
      "best_val": 0.00015338046597350536,
      "delta": NaN,
      "patience_left": 25,
      "improved": true,
      "learning_rate": 0.001
    },
    {
      "epoch": 2,
      "train_loss": 0.00012476632377211072,
      "val_loss": 0.0001349123657227894,
      "val_loss_for_stop": 0.00014414641584814737,
      "best_val": 0.00015338046597350536,
      "delta": -9.234050125357993e-06,
      "patience_left": 25,
      "improved": false,
      "learning_rate": 0.001
    },
    {
      "epoch": 3,
      "train_loss": 0.00011898648715732554,
      "val_loss": 0.00013996889322374616,
      "val_loss_for_stop": 0.0001427539083066803,
      "best_val": 0.0001427539083066803,
      "delta": -1.0626557666825061e-05,
      "patience_left": 25,
      "improved": true,
      "learning_rate": 0.001
    },
    {
      "epoch": 4,
      "train_loss": 0.00012329929146660178,
      "val_loss": 0.0001351841209056568,
      "val_loss_for_stop": 0.00013668845995073079,
      "best_val": 0.0001427539083066803,
      "delta": -6.065448355949512e-06,
      "patience_left": 25,
      "improved": false,
      "learning_rate": 0.001
    },
    {
      "epoch": 5,
      "train_loss": 0.0001224570637630645,
      "val_loss": 0.00013482533393486417,
      "val_loss_for_stop": 0.0001366594493547557,
      "best_val": 0.0001427539083066803,
      "delta": -6.094458951924587e-06,
      "patience_left": 25,
      "improved": false,
      "learning_rate": 0.001
    },
    {
      "epoch": 6,
      "train_loss": 0.0001240187746202738,
      "val_loss": 0.00014789892954189976,
      "val_loss_for_stop": 0.00013930279479414025,
      "best_val": 0.0001427539083066803,
      "delta": -3.4511135125400434e-06,
      "patience_left": 25,
      "improved": false,
      "learning_rate": 0.001
    },
    {
      "epoch": 7,
      "train_loss": 0.00012218499991453491,
      "val_loss": 0.00015036829632768516,
      "val_loss_for_stop": 0.00014436418660148303,
      "best_val": 0.0001427539083066803,
      "delta": 1.6102782948027364e-06,
      "patience_left": 25,
      "improved": false,
      "learning_rate": 0.001
    },
    {
      "epoch": 8,
      "train_loss": 0.00012243630266923507,
      "val_loss": 0.00014485319452658526,
      "val_loss_for_stop": 0.0001477068067987234,
      "best_val": 0.0001427539083066803,
      "delta": 4.952898492043098e-06,
      "patience_left": 25,
      "improved": false,
      "learning_rate": 0.001
    },
    {
      "epoch": 9,
      "train_loss": 0.00012283522556371063,
      "val_loss": 0.000154645533290353,
      "val_loss_for_stop": 0.00014995567471487448,
      "best_val": 0.0001427539083066803,
      "delta": 7.201766408194179e-06,
      "patience_left": 25,
      "improved": false,
      "learning_rate": 0.001
    },
    {
      "epoch": 10,
      "train_loss": 0.00012645921354072345,
      "val_loss": 0.0001359349724315665,
      "val_loss_for_stop": 0.00014514456674950157,
      "best_val": 0.0001427539083066803,
      "delta": 2.3906584428212718e-06,
      "patience_left": 25,
      "improved": false,
      "learning_rate": 0.001
    },
    {
      "epoch": 11,
      "train_loss": 0.00012549053988856289,
      "val_loss": 0.00013662761315166535,
      "val_loss_for_stop": 0.00014240270629119496,
      "best_val": 0.0001427539083066803,
      "delta": -3.512020154853375e-07,
      "patience_left": 25,
      "improved": false,
      "learning_rate": 0.0005
    },
    {
      "epoch": 12,
      "train_loss": 0.00012533082314859664,
      "val_loss": 0.00014657992172085733,
      "val_loss_for_stop": 0.00013971416910136305,
      "best_val": 0.0001427539083066803,
      "delta": -3.0397392053172466e-06,
      "patience_left": 25,
      "improved": false,
      "learning_rate": 0.0005
    },
    {
      "epoch": 13,
      "train_loss": 0.0001196257726998126,
      "val_loss": 0.00013783594238266834,
      "val_loss_for_stop": 0.00014034782575173034,
      "best_val": 0.0001427539083066803,
      "delta": -2.406082554949954e-06,
      "patience_left": 25,
      "improved": false,
      "learning_rate": 0.0005
    },
    {
      "epoch": 14,
      "train_loss": 0.00012189172314937366,
      "val_loss": 0.00014017363630181316,
      "val_loss_for_stop": 0.0001415298334684463,
      "best_val": 0.0001427539083066803,
      "delta": -1.224074838233999e-06,
      "patience_left": 25,
      "improved": false,
      "learning_rate": 0.0005
    },
    {
      "epoch": 15,
      "train_loss": 0.0001217096247936937,
      "val_loss": 0.0001348536785101241,
      "val_loss_for_stop": 0.0001376210857315352,
      "best_val": 0.0001427539083066803,
      "delta": -5.1328225751451015e-06,
      "patience_left": 25,
      "improved": false,
      "learning_rate": 0.0005
    },
    {
      "epoch": 16,
      "train_loss": 0.00012055102834144228,
      "val_loss": 0.00013523294587647504,
      "val_loss_for_stop": 0.00013675342022947078,
      "best_val": 0.0001427539083066803,
      "delta": -6.000488077209518e-06,
      "patience_left": 25,
      "improved": false,
      "learning_rate": 0.0005
    },
    {
      "epoch": 17,
      "train_loss": 0.00011916811013026616,
      "val_loss": 0.00013468695819750235,
      "val_loss_for_stop": 0.00013492452752803384,
      "best_val": 0.0001427539083066803,
      "delta": -7.829380778646457e-06,
      "patience_left": 25,
      "improved": false,
      "learning_rate": 0.0005
    },
    {
      "epoch": 18,
      "train_loss": 0.00012115239081244948,
      "val_loss": 0.00013663482678859796,
      "val_loss_for_stop": 0.00013551824362085846,
      "best_val": 0.0001427539083066803,
      "delta": -7.235664685821839e-06,
      "patience_left": 25,
      "improved": false,
      "learning_rate": 0.0005
    },
    {
      "epoch": 19,
      "train_loss": 0.00012063727451156644,
      "val_loss": 0.0001350295504019692,
      "val_loss_for_stop": 0.0001354504451293565,
      "best_val": 0.0001427539083066803,
      "delta": -7.303463177323787e-06,
      "patience_left": 25,
      "improved": false,
      "learning_rate": 0.0005
    },
    {
      "epoch": 20,
      "train_loss": 0.00012043637851463318,
      "val_loss": 0.00013692943803332976,
      "val_loss_for_stop": 0.00013619793840796563,
      "best_val": 0.0001427539083066803,
      "delta": -6.555969898714667e-06,
      "patience_left": 24,
      "improved": false,
      "learning_rate": 0.0005
    },
    {
      "epoch": 21,
      "train_loss": 0.0001225420090383273,
      "val_loss": 0.00013618625362893404,
      "val_loss_for_stop": 0.000136048414021411,
      "best_val": 0.0001427539083066803,
      "delta": -6.705494285269288e-06,
      "patience_left": 23,
      "improved": false,
      "learning_rate": 0.0005
    },
    {
      "epoch": 22,
      "train_loss": 0.00011996624124621709,
      "val_loss": 0.0001348251991973582,
      "val_loss_for_stop": 0.00013598029695320734,
      "best_val": 0.0001427539083066803,
      "delta": -6.773611353472957e-06,
      "patience_left": 22,
      "improved": false,
      "learning_rate": 0.0005
    },
    {
      "epoch": 23,
      "train_loss": 0.00011995737923672876,
      "val_loss": 0.00013434085476622063,
      "val_loss_for_stop": 0.00013511743586417096,
      "best_val": 0.0001427539083066803,
      "delta": -7.636472442509342e-06,
      "patience_left": 21,
      "improved": false,
      "learning_rate": 0.00025
    },
    {
      "epoch": 24,
      "train_loss": 0.0001178445518392847,
      "val_loss": 0.0001428847002492802,
      "val_loss_for_stop": 0.00013735025140428634,
      "best_val": 0.0001427539083066803,
      "delta": -5.40365690239396e-06,
      "patience_left": 20,
      "improved": false,
      "learning_rate": 0.00025
    },
    {
      "epoch": 25,
      "train_loss": 0.00011832494587319144,
      "val_loss": 0.00013487280392393948,
      "val_loss_for_stop": 0.0001373661196464801,
      "best_val": 0.0001427539083066803,
      "delta": -5.3877886602001965e-06,
      "patience_left": 19,
      "improved": false,
      "learning_rate": 0.00025
    },
    {
      "epoch": 26,
      "train_loss": 0.00011802016037945899,
      "val_loss": 0.00013900230498455296,
      "val_loss_for_stop": 0.00013891993638592422,
      "best_val": 0.0001427539083066803,
      "delta": -3.8339719207560775e-06,
      "patience_left": 18,
      "improved": false,
      "learning_rate": 0.00025
    },
    {
      "epoch": 27,
      "train_loss": 0.00011834231244304333,
      "val_loss": 0.00013430106661293064,
      "val_loss_for_stop": 0.00013605872517380769,
      "best_val": 0.0001427539083066803,
      "delta": -6.695183132872612e-06,
      "patience_left": 17,
      "improved": false,
      "learning_rate": 0.00025
    },
    {
      "epoch": 28,
      "train_loss": 0.00011818767589644686,
      "val_loss": 0.00013457214551057073,
      "val_loss_for_stop": 0.00013595850570268477,
      "best_val": 0.0001427539083066803,
      "delta": -6.79540260399553e-06,
      "patience_left": 16,
      "improved": false,
      "learning_rate": 0.00025
    },
    {
      "epoch": 29,
      "train_loss": 0.00011875123783340266,
      "val_loss": 0.00013498596442730574,
      "val_loss_for_stop": 0.0001346197255169357,
      "best_val": 0.0001427539083066803,
      "delta": -8.134182789744604e-06,
      "patience_left": 15,
      "improved": false,
      "learning_rate": 0.00025
    },
    {
      "epoch": 30,
      "train_loss": 0.00011982863789282129,
      "val_loss": 0.00013440308228547854,
      "val_loss_for_stop": 0.00013465373074111832,
      "best_val": 0.0001427539083066803,
      "delta": -8.100177565561979e-06,
      "patience_left": 14,
      "improved": false,
      "learning_rate": 0.00025
    },
    {
      "epoch": 31,
      "train_loss": 0.00011803170194255963,
      "val_loss": 0.0001369338745033861,
      "val_loss_for_stop": 0.00013544097373872346,
      "best_val": 0.0001427539083066803,
      "delta": -7.312934567956837e-06,
      "patience_left": 13,
      "improved": false,
      "learning_rate": 0.00025
    },
    {
      "epoch": 32,
      "train_loss": 0.00012034458903836878,
      "val_loss": 0.0001375498227757779,
      "val_loss_for_stop": 0.0001362955931882142,
      "best_val": 0.0001427539083066803,
      "delta": -6.458315118466109e-06,
      "patience_left": 12,
      "improved": false,
      "learning_rate": 0.00025
    },
    {
      "epoch": 33,
      "train_loss": 0.00011912601989636247,
      "val_loss": 0.0001343259915843229,
      "val_loss_for_stop": 0.00013626989628782895,
      "best_val": 0.0001427539083066803,
      "delta": -6.484012018851342e-06,
      "patience_left": 11,
      "improved": false,
      "learning_rate": 0.00025
    },
    {
      "epoch": 34,
      "train_loss": 0.00011978484891179643,
      "val_loss": 0.0001408501599760426,
      "val_loss_for_stop": 0.00013757532477871447,
      "best_val": 0.0001427539083066803,
      "delta": -5.178583527965826e-06,
      "patience_left": 10,
      "improved": false,
      "learning_rate": 0.00025
    },
    {
      "epoch": 35,
      "train_loss": 0.00011842362628979258,
      "val_loss": 0.00013741224955850134,
      "val_loss_for_stop": 0.00013752946703962229,
      "best_val": 0.0001427539083066803,
      "delta": -5.224441267058012e-06,
      "patience_left": 9,
      "improved": false,
      "learning_rate": 0.000125
    },
    {
      "epoch": 36,
      "train_loss": 0.00011761098658661894,
      "val_loss": 0.00013759319947345553,
      "val_loss_for_stop": 0.0001386185363359998,
      "best_val": 0.0001427539083066803,
      "delta": -4.135371970680494e-06,
      "patience_left": 8,
      "improved": false,
      "learning_rate": 0.000125
    },
    {
      "epoch": 37,
      "train_loss": 0.00011994930979150834,
      "val_loss": 0.0001348676228768785,
      "val_loss_for_stop": 0.0001366243573029451,
      "best_val": 0.0001427539083066803,
      "delta": -6.129551003735187e-06,
      "patience_left": 7,
      "improved": false,
      "learning_rate": 0.000125
    },
    {
      "epoch": 38,
      "train_loss": 0.00011858615339156734,
      "val_loss": 0.00013777327326690194,
      "val_loss_for_stop": 0.00013674469853907866,
      "best_val": 0.0001427539083066803,
      "delta": -6.009209767601634e-06,
      "patience_left": 6,
      "improved": false,
      "learning_rate": 0.000125
    },
    {
      "epoch": 39,
      "train_loss": 0.0001175473144948091,
      "val_loss": 0.00013432742904896717,
      "val_loss_for_stop": 0.00013565610839758253,
      "best_val": 0.0001427539083066803,
      "delta": -7.097799909097771e-06,
      "patience_left": 5,
      "improved": false,
      "learning_rate": 0.000125
    },
    {
      "epoch": 40,
      "train_loss": 0.0001201670208613108,
      "val_loss": 0.0001362898771317718,
      "val_loss_for_stop": 0.00013613019314921365,
      "best_val": 0.0001427539083066803,
      "delta": -6.623715157466647e-06,
      "patience_left": 4,
      "improved": false,
      "learning_rate": 0.000125
    },
    {
      "epoch": 41,
      "train_loss": 0.00011898036136634985,
      "val_loss": 0.0001353630605997991,
      "val_loss_for_stop": 0.00013532678892684604,
      "best_val": 0.0001427539083066803,
      "delta": -7.42711937983426e-06,
      "patience_left": 3,
      "improved": false,
      "learning_rate": 6.25e-05
    },
    {
      "epoch": 42,
      "train_loss": 0.00011757718412302418,
      "val_loss": 0.00013473413367265036,
      "val_loss_for_stop": 0.00013546235713474044,
      "best_val": 0.0001427539083066803,
      "delta": -7.291551171939857e-06,
      "patience_left": 2,
      "improved": false,
      "learning_rate": 6.25e-05
    },
    {
      "epoch": 43,
      "train_loss": 0.00011794870465105828,
      "val_loss": 0.00013431020247969345,
      "val_loss_for_stop": 0.00013480246558404763,
      "best_val": 0.0001427539083066803,
      "delta": -7.951442722632662e-06,
      "patience_left": 1,
      "improved": false,
      "learning_rate": 6.25e-05
    },
    {
      "epoch": 44,
      "train_loss": 0.00011756729249341776,
      "val_loss": 0.0001343076001522747,
      "val_loss_for_stop": 0.00013445064543487283,
      "best_val": 0.0001427539083066803,
      "delta": -8.30326287180747e-06,
      "patience_left": 0,
      "improved": false,
      "learning_rate": 6.25e-05
    }
  ]
}